Metadata-Version: 2.4
Name: py_ballisticcalc
Version: 2.2.8
Summary: LGPL library for small arms ballistic calculations (Python 3)
Author-email: o-murphy <thehelixpg@gmail.com>, dbookstaber <bookstaber@gmail.com>
License:                    GNU LESSER GENERAL PUBLIC LICENSE
Project-URL: Homepage, https://github.com/o-murphy/py-ballisticcalc
Project-URL: Documentation, https://o-murphy.github.io/py-ballisticcalc
Project-URL: Bug Reports, https://github.com/o-murphy/py-ballisticcalc/issues
Project-URL: Source, https://github.com/o-murphy/py-ballisticcalc
Keywords: py_ballisticcalc,ballistics,Cython,ballistic calculator,python,ballistic solver
Classifier: Intended Audience :: Developers
Classifier: Natural Language :: English
Classifier: Programming Language :: Python
Classifier: Topic :: Software Development :: Libraries :: Python Modules
Classifier: Programming Language :: Python :: 3
Classifier: Programming Language :: Python :: 3 :: Only
Classifier: Programming Language :: Python :: 3.10
Classifier: Programming Language :: Python :: 3.11
Classifier: Programming Language :: Python :: 3.12
Classifier: Programming Language :: Python :: 3.13
Classifier: Programming Language :: Python :: 3.14
Classifier: Operating System :: OS Independent
Classifier: Programming Language :: Python :: Implementation :: CPython
Requires-Python: >=3.10
License-File: LICENSE
Requires-Dist: typing_extensions>=4.12.2
Requires-Dist: tomli>=2.2.1; python_version < "3.11"
Requires-Dist: Deprecated>=1.2.18
Provides-Extra: exts
Requires-Dist: py_ballisticcalc.exts==2.2.8; extra == "exts"
Provides-Extra: charts
Requires-Dist: matplotlib>=3.10.7; extra == "charts"
Requires-Dist: pillow>=11.3.0; (python_version >= "3.13" and sys_platform == "win32") and extra == "charts"
Requires-Dist: pandas>=2.3.3; extra == "charts"
Requires-Dist: numpy>=2.2.6; extra == "charts"
Requires-Dist: numpy>=2.3.4; python_version >= "3.14" and extra == "charts"
Requires-Dist: scipy>=1.15.3; extra == "charts"
Provides-Extra: scipy
Requires-Dist: numpy>=2.2.6; extra == "scipy"
Requires-Dist: numpy>=2.3.4; python_version >= "3.14" and extra == "scipy"
Requires-Dist: scipy>=1.15.3; extra == "scipy"
Provides-Extra: dev
Requires-Dist: Cython>=3.1.4; extra == "dev"
Requires-Dist: build>=1.3.0; extra == "dev"
Requires-Dist: matplotlib>=3.10.7; extra == "dev"
Requires-Dist: pillow>=11.3.0; (python_version >= "3.13" and sys_platform == "win32") and extra == "dev"
Requires-Dist: pandas>=2.3.3; extra == "dev"
Requires-Dist: numpy>=2.2.6; extra == "dev"
Requires-Dist: numpy>=2.3.4; python_version >= "3.14" and extra == "dev"
Requires-Dist: scipy>=1.15.3; extra == "dev"
Requires-Dist: ipykernel; extra == "dev"
Requires-Dist: nbformat; extra == "dev"
Requires-Dist: mypy>=1.18.2; extra == "dev"
Requires-Dist: pylint>=4.0.1; extra == "dev"
Requires-Dist: pytest>=8.4.2; extra == "dev"
Requires-Dist: pytest-cov>=7.0.0; extra == "dev"
Requires-Dist: pytest-xdist>=3.8.0; extra == "dev"
Requires-Dist: ruff>=0.14.0; extra == "dev"
Requires-Dist: cython-lint>=0.18.1; extra == "dev"
Requires-Dist: pre-commit>=4.5.0; extra == "dev"
Requires-Dist: scipy-stubs>=1.16.2.3; python_version >= "3.11" and extra == "dev"
Requires-Dist: types-deprecated>=1.2.15.20250304; extra == "dev"
Requires-Dist: pandas-stubs>=2.3.2.250926; extra == "dev"
Provides-Extra: docs
Requires-Dist: mkdocs-mermaid2-plugin>=1.2.3; extra == "docs"
Requires-Dist: mkdocs>=1.6.1; extra == "docs"
Requires-Dist: mkdocs-exclude>=1.0.2; extra == "docs"
Requires-Dist: mkdocs-material[imaging]>=9.7.0; extra == "docs"
Requires-Dist: mkdocs-redirects>=1.2.2; extra == "docs"
Requires-Dist: mkdocstrings>=1.0.0; extra == "docs"
Requires-Dist: mkdocstrings-python>=2.0.0; extra == "docs"
Requires-Dist: mkdocs-autorefs>=1.4.3; extra == "docs"
Requires-Dist: mike>=2.1.3; extra == "docs"
Requires-Dist: pydocstyle>=6.3.0; extra == "docs"
Requires-Dist: mkdocs-macros-plugin>=1.3.7; extra == "docs"
Requires-Dist: setuptools-scm>=9.2; extra == "docs"
Dynamic: license-file
Dynamic: provides-extra
